{
    "common_images": [
        {
            "id": "profileImg",
            "title": "Maximiliano Malvicino",
            "alt": "Profile picture of Maximiliano Malvicino.",
            "src": "https://avatars.githubusercontent.com/u/46000191"
        },
        {
            "id": "logoImg",
            "title": "M. R. Malvicino",
            "alt": "Maximiliano Malvicino's personal logo.",
            "src": "./assets/images/logo.png"
        }
    ],
    "technologies_images": [
        {
            "id": "cppImg",
            "title": "C++",
            "alt": "C++ Logo.",
            "src": "https://raw.githubusercontent.com/devicons/devicon/master/icons/cplusplus/cplusplus-original.svg"
        },
        {
            "id": "csImg",
            "title": "C#",
            "alt": "C# Logo.",
            "src": "https://raw.githubusercontent.com/devicons/devicon/master/icons/csharp/csharp-original.svg"
        },
        {
            "id": "pythonImg",
            "title": "Python",
            "alt": "Python Logo.",
            "src": "https://raw.githubusercontent.com/devicons/devicon/master/icons/python/python-original.svg"
        },
        {
            "id": "javaImg",
            "title": "Java",
            "alt": "Java Logo.",
            "src": "https://raw.githubusercontent.com/devicons/devicon/master/icons/java/java-original.svg"
        },
        {
            "id": "jsImg",
            "title": "JavaScript",
            "alt": "JavaScript Logo.",
            "src": "https://raw.githubusercontent.com/devicons/devicon/master/icons/javascript/javascript-original.svg"
        },
        {
            "id": "htmlImg",
            "title": "HTML",
            "alt": "HTML Logo.",
            "src": "https://raw.githubusercontent.com/devicons/devicon/master/icons/html5/html5-original-wordmark.svg"
        },
        {
            "id": "cssImg",
            "title": "CSS",
            "alt": "CSS Logo.",
            "src": "https://raw.githubusercontent.com/devicons/devicon/master/icons/css3/css3-original-wordmark.svg"
        },
        {
            "id": "bootstrapImg",
            "title": "Bootstrap",
            "alt": "Bootstrap Logo.",
            "src": "https://upload.wikimedia.org/wikipedia/commons/thumb/b/b2/Bootstrap_logo.svg/1200px-Bootstrap_logo.svg.png"
        },
        {
            "id": "tailwindImg",
            "title": "Tailwind",
            "alt": "Tailwind Logo.",
            "src": "https://www.vectorlogo.zone/logos/tailwindcss/tailwindcss-icon.svg"
        },
        {
            "id": "dotnetImg",
            "title": "Microsoft .Net",
            "alt": "Microsoft .Net Logo.",
            "src": "https://raw.githubusercontent.com/devicons/devicon/master/icons/dot-net/dot-net-original-wordmark.svg"
        },
        {
            "id": "mssqlImg",
            "title": "Microsoft SQL Server",
            "alt": "Microsoft SQL Server Logo.",
            "src": "https://www.svgrepo.com/show/303229/microsoft-sql-server-logo.svg"
        },
        {
            "id": "mysqlImg",
            "title": "MySQL",
            "alt": "MySQL Logo.",
            "src": "https://raw.githubusercontent.com/devicons/devicon/master/icons/mysql/mysql-original-wordmark.svg"
        },
        {
            "id": "gitImg",
            "title": "Git",
            "alt": "Git Logo.",
            "src": "https://www.vectorlogo.zone/logos/git-scm/git-scm-icon.svg"
        },
        {
            "id": "latexImg",
            "title": "LaTex",
            "alt": "LaTex Logo.",
            "src": "https://cdn.pixabay.com/photo/2013/03/30/00/10/latex-97866_640.png"
        },
        {
            "id": "overleafImg",
            "title": "Overleaf",
            "alt": "Overleaf Logo.",
            "src": "https://images.ctfassets.net/nrgyaltdicpt/wwNSIPYEZa2OCOsuGweSY/0142fa5bce2f40f4168bad08acc8a52d/Sticker_square_colour_light_bg.png"
        }
    ],
    "institutions_images": [
        {
            "id": "untrefImg",
            "title": "Untref",
            "alt": "Untref Logo.",
            "src": "./assets/images/untref.png"
        },
        {
            "id": "utnImg",
            "title": "UTN",
            "alt": "UTN Logo.",
            "src": "./assets/images/utn.png"
        },
        {
            "id": "educacionitImg",
            "title": "Educacion IT",
            "alt": "Educacion IT Logo.",
            "src": "./assets/images/educacionit.svg"
        },
        {
            "id": "cambridgeImg",
            "title": "Cambridge",
            "alt": "Cambridge Logo.",
            "src": "./assets/images/cambridge.png"
        }
    ],
    "projects_images": [
        {
            "id": "wipImg",
            "title": "WIP",
            "alt": "Work In Progress sign.",
            "src": "https://t3.ftcdn.net/jpg/02/33/17/50/360_F_233175040_hwqRyiZlQkXimeLz2AIZhajyfiU9El1m.jpg"
        },
        {
            "id": "stusImg",
            "title": "STUS Calculator",
            "alt": "Graph of a Fourier approximation to a square wave.",
            "src": "https://github.com/mrmalvicino/stus-calculator/blob/main/images/dim_11.png?raw=true"
        },
        {
            "id": "ancImg",
            "title": "ANC Research Plan",
            "alt": "Bar graph of a Chi Square statistical analysis.",
            "src": "https://github.com/mrmalvicino/anc-research-plan/blob/main/Latex/images/cross_Y2.png?raw=true"
        },
        {
            "id": "dugunImg",
            "title": "Dugun Auto Clicker",
            "alt": "C++ code snippet with a class representing a timer.",
            "src": "https://i.imgur.com/EwCy5hL.png"
        },
        {
            "id": "binaryImg",
            "title": "Binary Calculator",
            "alt": "C++ code snippet with dynamic pointers and arrays.",
            "src": "https://i.imgur.com/PmQGGe1.png"
        },
        {
            "id": "balumaImg",
            "title": "Baluma ERP",
            "alt": "Terminal interface capture.",
            "src": "https://github.com/mrmalvicino/baluma-erp/raw/main/images/screenshot-stock.png?raw=true"
        },
        {
            "id": "irwinImg",
            "title": "Irwin's Revenge",
            "alt": "C++ code snippet with combined loops.",
            "src": "https://i.imgur.com/XiWHbjK.png"
        },
        {
            "id": "arduinoImg",
            "title": "Arduino LED Controller",
            "alt": "Photograph of a hand operating on an Arduino board.",
            "src": "https://content.instructables.com/FNO/ZIKG/K6HPDHBU/FNOZIKGK6HPDHBU.jpg?auto=webp&crop=1.2%3A1&frame=1&width=420"
        },
        {
            "id": "waveformImg",
            "title": "DSP Notes",
            "alt": "Waveform of a signal.",
            "src": "https://i.imgur.com/oWak3t1.png"
        },
        {
            "id": "transmissibilityImg",
            "title": "Acoustics Notes",
            "alt": "Vibration transmissibility curve.",
            "src": "https://i.imgur.com/1qQWsXr.png"
        },
        {
            "id": "circuitImg",
            "title": "Electronics Notes",
            "alt": "RLC circuit with alternating current source.",
            "src": "https://i.imgur.com/bXjmNw4.png"
        },
        {
            "id": "mathImg",
            "title": "Math Notes",
            "alt": "Two-surface graph.",
            "src": "https://i.imgur.com/2kqj9Xn.png"
        },
        {
            "id": "newtonImg",
            "title": "Physics Book",
            "alt": "Cover with a caricature of Isaac Newton",
            "src": "https://i.imgur.com/4WfJHib.png"
        },
        {
            "id": "planeImg",
            "title": "Physics 1 Solved",
            "alt": "Graph of an inclined plane with pulleys.",
            "src": "https://i.imgur.com/9WHXRsg.png"
        },
        {
            "id": "einsteinImg",
            "title": "Physics 2 Demonstrations",
            "alt": "Cover with a caricature of Albert Einstein.",
            "src": "https://i.imgur.com/Sq4x0DT.png"
        }
    ]
}